marko-2.1.3.dist-info/METADATA
marko-2.1.3.dist-info/WHEEL
marko-2.1.3.dist-info/entry_points.txt
marko-2.1.3.dist-info/licenses/LICENSE
marko/__init__.py
marko/__main__.py
marko/ast_renderer.py
marko/block.py
marko/cli.py
marko/element.py
marko/ext/__init__.py
marko/ext/codehilite.py
marko/ext/footnote.py
marko/ext/gfm/__init__.py
marko/ext/gfm/elements.py
marko/ext/gfm/renderer.py
marko/ext/latex_renderer.py
marko/ext/pangu.py
marko/ext/toc.py
marko/helpers.py
marko/html_renderer.py
marko/inline.py
marko/inline_parser.py
marko/md_renderer.py
marko/parser.py
marko/patterns.py
marko/py.typed
marko/renderer.py
marko/source.py
marko-2.1.3.dist-info/RECORD
