Metadata-Version: 2.1
Name: marko
Version: 2.1.3
Summary: A markdown parser with high extensibility.
Author-Email: Frost Ming <mianghong@gmail.com>
License: MIT
Classifier: Development Status :: 5 - Production/Stable
Classifier: Intended Audience :: Developers
Classifier: Operating System :: OS Independent
Classifier: Programming Language :: Python :: 3
Classifier: Programming Language :: Python :: 3.8
Classifier: Programming Language :: Python :: 3.9
Classifier: Programming Language :: Python :: 3.10
Classifier: Programming Language :: Python :: 3.11
Classifier: Programming Language :: Python :: 3.12
Project-URL: homepage, https://github.com/frostming/marko
Project-URL: Documentation, https://marko-py.readthedocs.io
Requires-Python: >=3.8
Provides-Extra: toc
Requires-Dist: python-slugify; extra == "toc"
Provides-Extra: codehilite
Requires-Dist: pygments; extra == "codehilite"
Provides-Extra: repr
Requires-Dist: objprint; extra == "repr"
